candbg/__init__.py
candbg/cli.py
candbg/inspector.py
candbg/py.typed
candbg/version.py
candbg-0.2.0.dist-info/LICENCE
candbg-0.2.0.dist-info/METADATA
candbg-0.2.0.dist-info/WHEEL
candbg-0.2.0.dist-info/entry_points.txt
candbg-0.2.0.dist-info/top_level.txt
candbg-0.2.0.dist-info/RECORD
