Metadata-Version: 2.2
Name: candbg
Version: 0.2.0
Summary: Debugging tools for can bus
Author-email: ROX Automation <jev.kuznetsov@gmail.com>
License: MIT
Project-URL: Homepage, https://gitlab.com/roxautomation/tools/candbg
Classifier: Development Status :: 3 - Alpha
Classifier: Intended Audience :: Developers
Classifier: Operating System :: OS Independent
Classifier: Programming Language :: Python
Classifier: Programming Language :: Python :: 3.10
Classifier: Topic :: Software Development :: Libraries :: Python Modules
Classifier: Typing :: Typed
Requires-Python: >=3.10
License-File: LICENCE
Requires-Dist: python-can
Requires-Dist: cantools
